fedn/__init__.py
fedn/cli/__init__.py
fedn/cli/client_cmd.py
fedn/cli/combiner_cmd.py
fedn/cli/config_cmd.py
fedn/cli/controller_cmd.py
fedn/cli/hooks_cmd.py
fedn/cli/login_cmd.py
fedn/cli/main.py
fedn/cli/model_cmd.py
fedn/cli/package_cmd.py
fedn/cli/project_cmd.py
fedn/cli/round_cmd.py
fedn/cli/run_cmd.py
fedn/cli/session_cmd.py
fedn/cli/shared.py
fedn/cli/status_cmd.py
fedn/cli/validation_cmd.py
fedn/cli/tests/__init__.py
fedn/cli/tests/tests.py
fedn/common/__init__.py
fedn/common/config.py
fedn/common/exceptions.py
fedn/common/log_config.py
fedn/common/settings-controller.yaml.template
fedn/common/certificate/__init__.py
fedn/common/certificate/certificate.py
fedn/common/certificate/certificatemanager.py
fedn/common/net/__init__.py
fedn/network/__init__.py
fedn/network/config.py
fedn/network/state.py
fedn/network/api/__init__.py
fedn/network/api/auth.py
fedn/network/api/client.py
fedn/network/api/gunicorn_app.py
fedn/network/api/network.py
fedn/network/api/server.py
fedn/network/api/shared.py
fedn/network/api/tests.py
fedn/network/api/v1/__init__.py
fedn/network/api/v1/attribute_routes.py
fedn/network/api/v1/client_routes.py
fedn/network/api/v1/combiner_routes.py
fedn/network/api/v1/helper_routes.py
fedn/network/api/v1/metric_routes.py
fedn/network/api/v1/model_routes.py
fedn/network/api/v1/package_routes.py
fedn/network/api/v1/prediction_routes.py
fedn/network/api/v1/round_routes.py
fedn/network/api/v1/run_routes.py
fedn/network/api/v1/session_routes.py
fedn/network/api/v1/shared.py
fedn/network/api/v1/status_routes.py
fedn/network/api/v1/telemetry_routes.py
fedn/network/api/v1/validation_routes.py
fedn/network/api/v1/graphql/__init__.py
fedn/network/api/v1/graphql/schema.py
fedn/network/clients/__init__.py
fedn/network/clients/client_v2.py
fedn/network/clients/connect.py
fedn/network/clients/fedn_client.py
fedn/network/clients/grpc_handler.py
fedn/network/clients/package_runtime.py
fedn/network/clients/state.py
fedn/network/combiner/__init__.py
fedn-0.32.0.dist-info/licenses/LICENSE
fedn-0.32.0.dist-info/METADATA
fedn-0.32.0.dist-info/WHEEL
fedn-0.32.0.dist-info/entry_points.txt
fedn-0.32.0.dist-info/top_level.txt
fedn-0.32.0.dist-info/RECORD
