Metadata-Version: 2.4
Name: fedn
Version: 0.32.0
Summary: Scaleout Federated Learning
Author-email: Scaleout Systems AB <contact@scaleoutsystems.com>
License: Copyright 2021 Scaleout Systems AB.  All rights reserved.
Project-URL: homepage, https://www.scaleoutsystems.com
Project-URL: documentation, https://fedn.readthedocs.io/en/stable/
Project-URL: repository, https://github.com/scaleoutsystems/fedn
Keywords: Scaleout,FEDn,Federated learning,FL,Machine learning
Classifier: Natural Language :: English
Classifier: Programming Language :: Python :: 3.9
Classifier: Programming Language :: Python :: 3.10
Classifier: Programming Language :: Python :: 3.11
Classifier: Programming Language :: Python :: 3.12
Requires-Python: <3.13,>=3.9
License-File: LICENSE
Requires-Dist: requests
Requires-Dist: urllib3>=1.26.4
Requires-Dist: gunicorn>=20.0.4
Requires-Dist: boto3==1.38.42
Requires-Dist: grpcio<=1.70,>=1.68.1
Requires-Dist: grpcio-tools<=1.70,>=1.68.1
Requires-Dist: numpy>=1.21.6
Requires-Dist: protobuf<6.31.0,>=5.0.0
Requires-Dist: pymongo
Requires-Dist: Flask==3.1.1
Requires-Dist: pyjwt
Requires-Dist: pyopenssl
Requires-Dist: psutil
Requires-Dist: click==8.1.8
Requires-Dist: grpcio-health-checking<=1.70,>=1.68.1
Requires-Dist: pyyaml
Requires-Dist: plotly
Requires-Dist: virtualenv
Requires-Dist: tenacity!=8.4.0
Requires-Dist: graphene>=3.1
Requires-Dist: SQLAlchemy>=2.0.36
Requires-Dist: psycopg2-binary>=2.9.10
Requires-Dist: opentelemetry-api
Requires-Dist: opentelemetry-sdk
Requires-Dist: opentelemetry-exporter-otlp
Dynamic: license-file
